dialga/__init__.py
dialga/scheduler.py
dialga/time.py
dialga/types.py
dialga-0.0.1.dist-info/METADATA
dialga-0.0.1.dist-info/WHEEL
dialga-0.0.1.dist-info/top_level.txt
dialga-0.0.1.dist-info/RECORD
