Metadata-Version: 2.1
Name: dialga
Version: 0.0.1
Summary: dialga
Home-page: https://github.com/NgHoangDat/dialga.git
Download-URL: https://github.com/NgHoangDat/dialga/archive/v0.0.1.tar.gz
Author: nghoangdat
Author-email: 18.hoang.dat.12@gmail.com
Classifier: Programming Language :: Python :: 3
Classifier: License :: OSI Approved :: MIT License
Classifier: Operating System :: OS Independent
Requires-Python: >=3.6
Requires-Dist: python-dateutil
Provides-Extra: dev
Requires-Dist: black ; extra == 'dev'
Requires-Dist: twine ; extra == 'dev'
